{
  "port-settings": {
    "K4": "ir-photo-reflector",
    "K6": "ir-photo-reflector",
    "V6": "buzzer"
  },
  "scripts": [
    {
      "name": "when-green-flag-clicked",
      "blocks": [
        {
          "name": "forever",
          "blocks": [
            {
              "name": "if-then-else",
              "condition": {
                "name": "greater-than?",
                "x": {
                  "name": "ir-photo-reflector-value",
                  "port": "K4"
                },
                "y": 30
              },
              "then-blocks": [
                {
                  "name": "if-then",
                  "condition": {
                    "name": "and",
                    "x": {
                      "name": "less-than?",
                      "x": 0,
                      "y": {
                        "name": "ir-photo-reflector-value",
                        "port": "K6"
                      }
                    },
                    "y": {
                      "name": "less-than?",
                      "x": {
                        "name": "ir-photo-reflector-value",
                        "port": "K6"
                      },
                      "y": 10
                    }
                  },
                  "blocks": [
                    {
                      "name": "buzzer-on",
                      "port": "V6",
                      "frequency": 57
                    }
                  ]
                },
                {
                  "name": "if-then",
                  "condition": {
                    "name": "and",
                    "x": {
                      "name": "less-than?",
                      "x": 9,
                      "y": {
                        "name": "ir-photo-reflector-value",
                        "port": "K6"
                      }
                    },
                    "y": {
                      "name": "less-than?",
                      "x": {
                        "name": "ir-photo-reflector-value",
                        "port": "K6"
                      },
                      "y": 11
                    }
                  },
                  "blocks": [
                    {
                      "name": "buzzer-on",
                      "port": "V6",
                      "frequency": 59
                    }
                  ]
                },
                {
                  "name": "if-then",
                  "condition": {
                    "name": "and",
                    "x": {
                      "name": "less-than?",
                      "x": 10,
                      "y": {
                        "name": "ir-photo-reflector-value",
                        "port": "K6"
                      }
                    },
                    "y": {
                      "name": "less-than?",
                      "x": {
                        "name": "ir-photo-reflector-value",
                        "port": "K6"
                      },
                      "y": 13
                    }
                  },
                  "blocks": [
                    {
                      "name": "buzzer-on",
                      "port": "V6",
                      "frequency": 60
                    }
                  ]
                },
                {
                  "name": "if-then",
                  "condition": {
                    "name": "and",
                    "x": {
                      "name": "less-than?",
                      "x": 12,
                      "y": {
                        "name": "ir-photo-reflector-value",
                        "port": "K6"
                      }
                    },
                    "y": {
                      "name": "less-than?",
                      "x": {
                        "name": "ir-photo-reflector-value",
                        "port": "K6"
                      },
                      "y": 15
                    }
                  },
                  "blocks": [
                    {
                      "name": "buzzer-on",
                      "port": "V6",
                      "frequency": 62
                    }
                  ]
                },
                {
                  "name": "if-then",
                  "condition": {
                    "name": "and",
                    "x": {
                      "name": "less-than?",
                      "x": 14,
                      "y": {
                        "name": "ir-photo-reflector-value",
                        "port": "K6"
                      }
                    },
                    "y": {
                      "name": "less-than?",
                      "x": {
                        "name": "ir-photo-reflector-value",
                        "port": "K6"
                      },
                      "y": 19
                    }
                  },
                  "blocks": [
                    {
                      "name": "buzzer-on",
                      "port": "V6",
                      "frequency": 64
                    }
                  ]
                },
                {
                  "name": "if-then",
                  "condition": {
                    "name": "and",
                    "x": {
                      "name": "less-than?",
                      "x": 18,
                      "y": {
                        "name": "ir-photo-reflector-value",
                        "port": "K6"
                      }
                    },
                    "y": {
                      "name": "less-than?",
                      "x": {
                        "name": "ir-photo-reflector-value",
                        "port": "K6"
                      },
                      "y": 24
                    }
                  },
                  "blocks": [
                    {
                      "name": "buzzer-on",
                      "port": "V6",
                      "frequency": 65
                    }
                  ]
                },
                {
                  "name": "if-then",
                  "condition": {
                    "name": "and",
                    "x": {
                      "name": "less-than?",
                      "x": 23,
                      "y": {
                        "name": "ir-photo-reflector-value",
                        "port": "K6"
                      }
                    },
                    "y": {
                      "name": "less-than?",
                      "x": {
                        "name": "ir-photo-reflector-value",
                        "port": "K6"
                      },
                      "y": 32
                    }
                  },
                  "blocks": [
                    {
                      "name": "buzzer-on",
                      "port": "V6",
                      "frequency": 67
                    }
                  ]
                },
                {
                  "name": "if-then",
                  "condition": {
                    "name": "and",
                    "x": {
                      "name": "less-than?",
                      "x": 31,
                      "y": {
                        "name": "ir-photo-reflector-value",
                        "port": "K6"
                      }
                    },
                    "y": {
                      "name": "less-than?",
                      "x": {
                        "name": "ir-photo-reflector-value",
                        "port": "K6"
                      },
                      "y": 43
                    }
                  },
                  "blocks": [
                    {
                      "name": "buzzer-on",
                      "port": "V6",
                      "frequency": 69
                    }
                  ]
                },
                {
                  "name": "if-then",
                  "condition": {
                    "name": "and",
                    "x": {
                      "name": "less-than?",
                      "x": 42,
                      "y": {
                        "name": "ir-photo-reflector-value",
                        "port": "K6"
                      }
                    },
                    "y": {
                      "name": "less-than?",
                      "x": {
                        "name": "ir-photo-reflector-value",
                        "port": "K6"
                      },
                      "y": 59
                    }
                  },
                  "blocks": [
                    {
                      "name": "buzzer-on",
                      "port": "V6",
                      "frequency": 71
                    }
                  ]
                },
                {
                  "name": "if-then",
                  "condition": {
                    "name": "less-than?",
                    "x": 58,
                    "y": {
                      "name": "ir-photo-reflector-value",
                      "port": "K6"
                    }
                  },
                  "blocks": [
                    {
                      "name": "buzzer-on",
                      "port": "V6",
                      "frequency": 72
                    }
                  ]
                }
              ],
              "else-blocks": [
                {
                  "name": "buzzer-off",
                  "port": "V6"
                }
              ]
            }
          ]
        }
      ]
    }
  ]
}
